ov7670_uart_test.srcs/sources_1/new/frame_buffer.v
`timescale 1ns / 1ps
// =============================================================================
// frame_buffer.v — Dual-Port BRAM, 320x240 @ 12-bit (RGB444)
//
// Port A: write port — driven by frame_capture, clocked by clk_a (100 MHz sys)
// Port B: read port  — driven by VGA controller, clocked by clk_b (25 MHz pix)
//
// True dual-port BRAM with independent clocks per port: the BRAM array itself
// performs the clock-domain crossing between the 100 MHz write side and the
// 25 MHz VGA read side, so no external synchronizers are required.
//
// 76800 entries × 12 bits = 900 Kbits ≈ 25 × 36Kb BRAM blocks on Basys 3.
// The (* ram_style = "block" *) attribute forces Vivado to use block RAM.
// =============================================================================
module frame_buffer (
    input  wire        clk_a,       // 100 MHz write-side clock (sys)
    input  wire        clk_b,       //  25 MHz read-side clock  (VGA pixel)

    // Port A — write (from frame_capture)
    input  wire        we_a,        // write enable
    input  wire [16:0] addr_a,      // write address, range 0..76799
    input  wire [11:0] din_a,       // 12-bit RGB444 pixel to write

    // Port B — read (from VGA / pixel_scaler)
    input  wire [16:0] addr_b,      // read address, range 0..76799
    output reg  [11:0] dout_b       // 12-bit RGB444 pixel (1-cycle latency)
);

    // 76800 entries × 12 bits
    (* ram_style = "block" *)
    reg [11:0] mem [0:76799];

    // Port A: synchronous write on 100 MHz sys clock
    always @(posedge clk_a) begin
        if (we_a)
            mem[addr_a] <= din_a;
    end

    // Port B: synchronous read on 25 MHz VGA clock — output registered
    // dout_b is valid 1 clk_b cycle after addr_b is presented
    always @(posedge clk_b) begin
        dout_b <= mem[addr_b];
    end

endmodule

ov7670_uart_test.srcs/sim_1/new/tb_frame_buffer.v
`timescale 1ns / 1ps
// =============================================================================
// tb_frame_buffer.v — Testbench for frame_buffer
//
// Tests:
//   1. Sequential writes then read-back (verifies 1-cycle read latency)
//   2. Simultaneous read/write to different addresses
//   3. Frame corner addresses (addr 0, 319, 76480, 76799)
// =============================================================================
module tb_frame_buffer;

    // -------------------------------------------------------------------------
    // DUT signals
    // -------------------------------------------------------------------------
    reg        clk_a;       // 100 MHz write-side clock
    reg        clk_b;       //  25 MHz read-side clock
    reg        we_a;
    reg [16:0] addr_a;
    reg [11:0] din_a;
    reg [16:0] addr_b;
    wire[11:0] dout_b;

    // -------------------------------------------------------------------------
    // DUT instantiation
    // -------------------------------------------------------------------------
    frame_buffer dut (
        .clk_a  (clk_a),
        .clk_b  (clk_b),
        .we_a   (we_a),
        .addr_a (addr_a),
        .din_a  (din_a),
        .addr_b (addr_b),
        .dout_b (dout_b)
    );

    // -------------------------------------------------------------------------
    // Clocks: 100 MHz write port, 25 MHz read port
    // -------------------------------------------------------------------------
    initial clk_a = 0;
    always #5  clk_a = ~clk_a;   // 10 ns period -> 100 MHz

    initial clk_b = 0;
    always #20 clk_b = ~clk_b;   // 40 ns period ->  25 MHz

    // -------------------------------------------------------------------------
    // Pass/fail tracking
    // -------------------------------------------------------------------------
    integer errors;

    task check;
        input [16:0] addr;
        input [11:0] expected;
        input [11:0] got;
        begin
            if (got !== expected) begin
                $display("FAIL  addr=%0d  expected=%03h  got=%03h", addr, expected, got);
                errors = errors + 1;
            end else begin
                $display("PASS  addr=%0d  value=%03h", addr, got);
            end
        end
    endtask

    // -------------------------------------------------------------------------
    // Test sequence
    // -------------------------------------------------------------------------
    initial begin
        errors = 0;
        we_a   = 0;
        addr_a = 0;
        din_a  = 0;
        addr_b = 0;

        // ------------------------------------------------------------------
        // Test 1: Write several pixels on clk_a, then read them back on clk_b
        // ------------------------------------------------------------------
        $display("--- Test 1: sequential write (clk_a) then read-back (clk_b) ---");

        @(posedge clk_a); #1;
        we_a = 1; addr_a = 17'd0;     din_a = 12'hABC;
        @(posedge clk_a); #1;
        we_a = 1; addr_a = 17'd1;     din_a = 12'hDEF;
        @(posedge clk_a); #1;
        we_a = 1; addr_a = 17'd76799; din_a = 12'hF0F;  // last valid address
        @(posedge clk_a); #1;
        we_a = 0;

        // Read addr 0: set addr_b, wait one clk_b edge, then sample
        addr_b = 17'd0;
        @(posedge clk_b); #1;
        check(0, 12'hABC, dout_b);

        addr_b = 17'd1;
        @(posedge clk_b); #1;
        check(1, 12'hDEF, dout_b);

        addr_b = 17'd76799;
        @(posedge clk_b); #1;
        check(76799, 12'hF0F, dout_b);

        // ------------------------------------------------------------------
        // Test 2: Concurrent write (clk_a) and read (clk_b) on DIFFERENT addrs
        // (typical operation: frame_capture writing while VGA is reading)
        // ------------------------------------------------------------------
        $display("--- Test 2: simultaneous read/write different addresses ---");

        // Pre-load addr 100
        @(posedge clk_a); #1;
        we_a = 1; addr_a = 17'd100; din_a = 12'h123;
        @(posedge clk_a); #1;
        we_a = 0;

        // Begin concurrent: write addr 200 on clk_a, read addr 100 on clk_b
        addr_b = 17'd100;
        we_a   = 1; addr_a = 17'd200; din_a = 12'h456;
        @(posedge clk_b); #1;
        check(100, 12'h123, dout_b);
        // 40 ns of clk_b waiting = 4 clk_a edges, so the addr-200 write committed
        we_a = 0;

        // Read back addr 200 on clk_b
        addr_b = 17'd200;
        @(posedge clk_b); #1;
        check(200, 12'h456, dout_b);

        // ------------------------------------------------------------------
        // Test 3: Frame corner addresses
        // Row 0 col 319 → addr = 319
        // Row 239 col 0 → addr = 239*320 = 76480
        // ------------------------------------------------------------------
        $display("--- Test 3: frame corner addresses ---");

        @(posedge clk_a); #1;
        we_a = 1; addr_a = 17'd319;   din_a = 12'hCAF;
        @(posedge clk_a); #1;
        we_a = 1; addr_a = 17'd76480; din_a = 12'hBEE;
        @(posedge clk_a); #1;
        we_a = 0;

        addr_b = 17'd319;
        @(posedge clk_b); #1;
        check(319, 12'hCAF, dout_b);

        addr_b = 17'd76480;
        @(posedge clk_b); #1;
        check(76480, 12'hBEE, dout_b);

        // ------------------------------------------------------------------
        // Summary
        // ------------------------------------------------------------------
        if (errors == 0)
            $display("=== ALL TESTS PASSED ===");
        else
            $display("=== %0d TEST(S) FAILED ===", errors);

        $finish;
    end

    // -------------------------------------------------------------------------
    // Waveform dump
    // -------------------------------------------------------------------------
    initial begin
        $dumpfile("tb_frame_buffer.vcd");
        $dumpvars(0, tb_frame_buffer);
    end

endmodule

ov7670_uart_test.sim/sim_1/behav/xsim/tb_frame_buffer.vcd
$date
   Sun May 10 12:18:59 2026
$end

$version
  2025.2
  $dumpfile ("tb_frame_buffer.vcd") 
$end

$timescale
  1ps
$end

$scope module tb_frame_buffer $end
$var reg 1 ! clk_a $end
$var reg 1 " clk_b $end
$var reg 1 # we_a $end
$var reg 17 $ addr_a [16:0] $end
$var reg 12 % din_a [11:0] $end
$var reg 17 & addr_b [16:0] $end
$var wire 12 ' dout_b [11:0] $end
$var integer 32 ( errors [31:0] $end
$scope module dut $end
$var wire 1 ) clk_a $end
$var wire 1 * clk_b $end
$var wire 1 + we_a $end
$var wire 17 , addr_a [16:0] $end
$var wire 12 - din_a [11:0] $end
$var wire 17 . addr_b [16:0] $end
$var reg 12 / dout_b [11:0] $end
$upscope $end
$scope task check $end
$var reg 17 0 addr [16:0] $end
$var reg 12 1 expected [11:0] $end
$var reg 12 2 got [11:0] $end
$upscope $end
$upscope $end
$enddefinitions $end

#0
$dumpvars
0!
0"
0#
b0 $
b0 %
b0 &
bx '
b0 (
0)
0*
0+
b0 ,
b0 -
b0 .
bx /
bx 0
bx 1
bx 2
$end

#5000
1!
1)

#6000
1#
b101010111100 %
1+
b101010111100 -

#10000
0!
0)

#15000
1!
1)

#16000
b1 $
b110111101111 %
b1 ,
b110111101111 -

#20000
0!
1"
b101010111100 '
0)
1*
b101010111100 /

#25000
1!
1)

#26000
b10010101111111111 $
b111100001111 %
b10010101111111111 ,
b111100001111 -

#30000
0!
0)

#35000
1!
1)

#36000
0#
0+

#40000
0!
0"
0)
0*

#45000
1!
1)

#50000
0!
0)

#55000
1!
1)

#60000
0!
1"
0)
1*

#61000
b1 &
b1 .
b0 0
b101010111100 1
b101010111100 2

#65000
1!
1)

#70000
0!
0)

#75000
1!
1)

#80000
0!
0"
0)
0*

#85000
1!
1)

#90000
0!
0)

#95000
1!
1)

#100000
0!
1"
b110111101111 '
0)
1*
b110111101111 /

#101000
b10010101111111111 &
b10010101111111111 .
b1 0
b110111101111 1
b110111101111 2

#105000
1!
1)

#110000
0!
0)

#115000
1!
1)

#120000
0!
0"
0)
0*

#125000
1!
1)

#130000
0!
0)

#135000
1!
1)

#140000
0!
1"
b111100001111 '
0)
1*
b111100001111 /

#141000
b10010101111111111 0
b111100001111 1
b111100001111 2

#145000
1!
1)

#146000
1#
b1100100 $
b100100011 %
1+
b1100100 ,
b100100011 -

#150000
0!
0)

#155000
1!
1)

#156000
1#
b11001000 $
b10001010110 %
b1100100 &
b11001000 ,
b10001010110 -
b1100100 .

#160000
0!
0"
0)
0*

#165000
1!
1)

#170000
0!
0)

#175000
1!
1)

#180000
0!
1"
b100100011 '
0)
1*
b100100011 /

#181000
0#
b11001000 &
0+
b11001000 .
b1100100 0
b100100011 1
b100100011 2

#185000
1!
1)

#190000
0!
0)

#195000
1!
1)

#200000
0!
0"
0)
0*

#205000
1!
1)

#210000
0!
0)

#215000
1!
1)

#220000
0!
1"
b10001010110 '
0)
1*
b10001010110 /

#221000
b11001000 0
b10001010110 1
b10001010110 2

#225000
1!
1)

#226000
1#
b100111111 $
b110010101111 %
1+
b100111111 ,
b110010101111 -

#230000
0!
0)

#235000
1!
1)

#236000
b10010101011000000 $
b101111101110 %
b10010101011000000 ,
b101111101110 -

#240000
0!
0"
0)
0*

#245000
1!
1)

#246000
0#
b100111111 &
0+
b100111111 .

#250000
0!
0)

#255000
1!
1)

#260000
0!
1"
b110010101111 '
0)
1*
b110010101111 /

#261000
b10010101011000000 &
b10010101011000000 .
b100111111 0
b110010101111 1
b110010101111 2

#265000
1!
1)

#270000
0!
0)

#275000
1!
1)

#280000
0!
0"
0)
0*

#285000
1!
1)

#290000
0!
0)

#295000
1!
1)

#300000
0!
1"
b101111101110 '
0)
1*
b101111101110 /

#301000
b10010101011000000 0
b101111101110 1
b101111101110 2
